shahr2/__init__.py
shahr2/pymailsender.py
shahr2.pymailsender-0.0.2.dist-info/LICENSE
shahr2.pymailsender-0.0.2.dist-info/METADATA
shahr2.pymailsender-0.0.2.dist-info/WHEEL
shahr2.pymailsender-0.0.2.dist-info/top_level.txt
shahr2.pymailsender-0.0.2.dist-info/RECORD
